srsinst/dc205/__init__.py
srsinst/dc205/__main__.py
srsinst/dc205/dc205.taskconfig
srsinst/dc205/instruments/__init__.py
srsinst/dc205/instruments/components.py
srsinst/dc205/instruments/dc205.py
srsinst/dc205/instruments/get_instruments.py
srsinst/dc205/instruments/keys.py
srsinst/dc205/tasks/setoutput.py
srsinst.dc205-0.0.5.dist-info/LICENSE.txt
srsinst.dc205-0.0.5.dist-info/METADATA
srsinst.dc205-0.0.5.dist-info/WHEEL
srsinst.dc205-0.0.5.dist-info/entry_points.txt
srsinst.dc205-0.0.5.dist-info/top_level.txt
srsinst.dc205-0.0.5.dist-info/RECORD
