Metadata-Version: 2.1
Name: srsinst.dc205
Version: 0.0.5
Summary: Instrument driver package for the DC205 DC Voltage Source from Stanford Research Systems (SRS)
Author: Chulhoon Kim
License: MIT license
Keywords: DC205,voltage source,SRS,Stanford Research Systems
Classifier: Development Status :: 3 - Alpha
Classifier: Intended Audience :: Science/Research
Classifier: License :: OSI Approved :: MIT License
Classifier: Programming Language :: Python :: 3.7
Classifier: Programming Language :: Python :: 3.8
Classifier: Programming Language :: Python :: 3.9
Classifier: Programming Language :: Python :: 3.10
Classifier: Topic :: Scientific/Engineering
Classifier: Topic :: Scientific/Engineering :: Chemistry
Classifier: Topic :: Scientific/Engineering :: Physics
Requires-Python: >=3.7
License-File: LICENSE.txt
Requires-Dist: srsgui >=0.4.1
Provides-Extra: full
Requires-Dist: matplotlib >=3.6.2 ; extra == 'full'
Requires-Dist: pyside6 ; extra == 'full'
